<?xml version="1.0" encoding="utf-8" ?>
<Defs>
    <HediffDef>
        <defName>HB_InfernalUtility</defName>
        <label>infernal utility</label>
        <description>Support hediff for the HellBionics ability structure</description>
        <hediffClass>HediffWithComps</hediffClass>
        <isBad>false</isBad>
        <defaultLabelColor>(1.0, 0.5, 0)</defaultLabelColor>
        <comps>
            <li Class="HellBionics.HediffCompProperties_InfernalUtility"/>
        </comps>
    </HediffDef>
</Defs>